<?xml version="1.0" encoding="UTF-8"?><record_update table="sp_instance">
    <sp_instance action="INSERT_OR_UPDATE">
        <active>true</active>
        <class_name/>
        <color>default</color>
        <css/>
        <glyph/>
        <id/>
        <order>1</order>
        <roles/>
        <short_description/>
        <size>md</size>
        <sp_column display_value="1">fd601ce707d57110151cfc018c1ed093</sp_column>
        <sp_widget display_value="Actions Widget">38a3a159530201101865ddeeff7b1263</sp_widget>
        <sys_class_name>sp_instance</sys_class_name>
        <sys_created_by>admin</sys_created_by>
        <sys_created_on>2023-09-21 09:45:33</sys_created_on>
        <sys_id>fb60d8a707d57110151cfc018c1ed0ac</sys_id>
        <sys_mod_count>1</sys_mod_count>
        <sys_name/>
        <sys_package display_value="HROB-POC" source="x_1106637_hrob_poc">b73392a507203110151cfc018c1ed083</sys_package>
        <sys_policy/>
        <sys_scope display_value="HROB-POC">b73392a507203110151cfc018c1ed083</sys_scope>
        <sys_update_name>sp_instance_fb60d8a707d57110151cfc018c1ed0ac</sys_update_name>
        <sys_updated_by>admin</sys_updated_by>
        <sys_updated_on>2023-09-22 09:00:51</sys_updated_on>
        <title/>
        <url/>
        <widget_parameters><![CDATA[{
	"action_group": {
		"value": "5db41e3a534201101865ddeeff7b124c",
		"displayValue": "Employee Profile Group"
	}
}]]></widget_parameters>
    </sp_instance>
    <sys_translated_text action="delete_multiple" query="documentkey=fb60d8a707d57110151cfc018c1ed0ac"/>
</record_update>
